{
    "เขื่อนภูมิพล": {
        "DAM_Name": "เขื่อนภูมิพล",
        "Dam_Province": "ตาก"
    },
    "เขื่อนสิริกิติ์": {
        "DAM_Name": "เขื่อนสิริกิติ์",
        "Dam_Province": "อุตรดิตถ์"
    },
    "เขื่อนแม่งัดสมบูรณ์ชล": {
        "DAM_Name": "เขื่อนแม่งัดสมบูรณ์ชล",
        "Dam_Province": "เชียงใหม่"
    },
    "เขื่อนแม่กวงอุดมธารา": {
        "DAM_Name": "เขื่อนแม่กวงอุดมธารา",
        "Dam_Province": "เชียงใหม่"
    },
    "เขื่อนกิ่วลม": {
        "DAM_Name": "เขื่อนกิ่วลม",
        "Dam_Province": "ลำปาง"
    },
    "เขื่อนกิ่วคอหมา": {
        "DAM_Name": "เขื่อนกิ่วคอหมา",
        "Dam_Province": "ลำปาง"
    },
    "เขื่อนแควน้อยบํารุงแดน": {
        "DAM_Name": "เขื่อนแควน้อยบํารุงแดน",
        "Dam_Province": "พิษณุโลก"
    },
    "เขื่อนแม่มอก": {
        "DAM_Name": "เขื่อนแม่มอก",
        "Dam_Province": "ลำปาง"
    },
    "เขื่อนน้ำพุง": {
        "DAM_Name": "เขื่อนน้ำพุง",
        "Dam_Province": "สกลนคร"
    },
    "เขื่อนจุฬาภรณ์": {
        "DAM_Name": "เขื่อนจุฬาภรณ์",
        "Dam_Province": "ชัยภูมิ"
    },
    "เขื่อนอุบลรัตน์": {
        "DAM_Name": "เขื่อนอุบลรัตน์",
        "Dam_Province": "ขอนแก่น,หนองบัวลำภู"
    },
    "เขื่อนสิรินธร": {
        "DAM_Name": "เขื่อนสิรินธร",
        "Dam_Province": "อุบลราชธานี"
    },
    "เขื่อนห้วยหลวง": {
        "DAM_Name": "เขื่อนห้วยหลวง",
        "Dam_Province": "อุดรธานี"
    },
    "เขื่อนน้ำอูน": {
        "DAM_Name": "เขื่อนน้ำอูน",
        "Dam_Province": "สกลนคร"
    },
    "เขื่อนลำปาว": {
        "DAM_Name": "เขื่อนลำปาว",
        "Dam_Province": "กาฬสินธุ์"
    },
    "เขื่อนลำตะคอง": {
        "DAM_Name": "เขื่อนลำตะคอง",
        "Dam_Province": "นครราชสีมา, สระบุรี"
    },
    "เขื่อนลำพระเพลิง": {
        "DAM_Name": "เขื่อนลำพระเพลิง",
        "Dam_Province": "นครราชสีมา"
    },
    "เขื่อนมูลบน": {
        "DAM_Name": "เขื่อนมูลบน",
        "Dam_Province": "นครราชสีมา"
    },
    "เขื่อนลำแซะ": {
        "DAM_Name": "เขื่อนลำแซะ",
        "Dam_Province": "นครราชสีมา"
    },
    "เขื่อนลำนางรอง": {
        "DAM_Name": "เขื่อนลำนางรอง",
        "Dam_Province": "บุรีรัมย์"
    },
    "เขื่อนป่าสักชลสิทธิ์": {
        "DAM_Name": "เขื่อนป่าสักชลสิทธิ์",
        "Dam_Province": "ลพบุรี "
    },
    "เขื่อนทับเสลา": {
        "DAM_Name": "เขื่อนทับเสลา",
        "Dam_Province": "อุทัยธานี"
    },
    "เขื่อนกระเสียว": {
        "DAM_Name": "เขื่อนกระเสียว",
        "Dam_Province": "สุพรรณบุรี"
    },
    "เขื่อนศรีนครินทร์": {
        "DAM_Name": "เขื่อนศรีนครินทร์",
        "Dam_Province": "กาญจนบุรี"
    },
    "เขื่อนวชิราลงกรณ์": {
        "DAM_Name": "เขื่อนวชิราลงกรณ์",
        "Dam_Province": "ลพบุรี "
    },
    "เขื่อนขุนด่านปราการชล": {
        "DAM_Name": "เขื่อนขุนด่านปราการชล",
        "Dam_Province": "นครนายก "
    },
    "เขื่อนคลองสียัด": {
        "DAM_Name": "เขื่อนคลองสียัด",
        "Dam_Province": "ฉะเชิงเทรา"
    },
    "เขื่อนบางพระ": {
        "DAM_Name": "เขื่อนบางพระ",
        "Dam_Province": "ชลบุรี"
    },
    "เขื่อนหนองปลาไหล": {
        "DAM_Name": "เขื่อนหนองปลาไหล",
        "Dam_Province": "ระยอง"
    },
    "เขื่อนประแสร์": {
        "DAM_Name": "เขื่อนประแสร์",
        "Dam_Province": "ระยอง"
    },
    "เขื่อนนฤบดินทร์จินดา": {
        "DAM_Name": "เขื่อนนฤบดินทร์จินดา",
        "Dam_Province": "ปราจีนบุรี"
    },
    "เขื่อนรัชชประภา": {
        "DAM_Name": "เขื่อนรัชชประภา",
        "Dam_Province": "สุราษฎร์ธานี"
    },
    "เขื่อนบางลาง": {
        "DAM_Name": "เขื่อนบางลาง",
        "Dam_Province": "ยะลา"
    },
    "เขื่อนแก่งกระจาน": {
        "DAM_Name": "เขื่อนแก่งกระจาน",
        "Dam_Province": "เพชรบุรี"
    },
    "เขื่อนปราณบุรี": {
        "DAM_Name": "เขื่อนปราณบุรี",
        "Dam_Province": "ประจวบคีรีขันธ์"
    }
}